README.md
setup.py
ut/__init__.py
ut/cli.py
ut.egg-info/PKG-INFO
ut.egg-info/SOURCES.txt
ut.egg-info/dependency_links.txt
ut.egg-info/entry_points.txt
ut.egg-info/requires.txt
ut.egg-info/top_level.txt