Metadata-Version: 2.1
Name: ut
Version: 0.2.0
Summary: Universal Toolbox.
Home-page: UNKNOWN
License: UNKNOWN
Platform: UNKNOWN
